Workbook

Sheet Cover
A1: ASET / GLOBAL EQUITY RESEARCH
A2: Original, provenance-first workbook • blank until official data is loaded
A4: Purpose | B4: Deep company research and worldwide equity screening with auditable source mapping.
A5: Data status | B5: TEMPLATE — no market figures or invented company data are included.
A6: Source rule | B6: Only official sources in data/official_source_registry.csv and ASET provider records.
A7: Scoring | B7: equity_v1: business 20%, financial quality 25%, valuation 20%, growth 15%, balance sheet 10%, risk 10%.
A8: Coverage gate | B8: Do not rank a company with less than 60% weighted data coverage; label 60–<80% provisional.
A9: Important | B9: Research only. No trade execution, personalized advice, or transaction capability.

Sheet Screen_Input
A1: SCREEN / INPUT
A2: Enter only verified values; blue text indicates user-entered source data
A4: Ticker | B4: Issuer | C4: Country | D4: Exchange | E4: Sector | F4: Currency | G4: As Of | H4: Source Ref | I4: Market Cap | J4: Revenue | K4: EBITDA Margin | L4: ROIC | M4: FCF Margin | N4: Net Debt / EBITDA | O4: Revenue CAGR 5Y | P4: P/E | Q4: EV / EBITDA | R4: Liquidity Note | S4: Data Status | T4: Analyst Note

Sheet Screen_Output
A1: SCREEN / OUTPUT
A2: Formula-driven ranking; blank or unverified records remain incomplete
A4: Ticker | B4: Issuer | C4: Eligibility | D4: Coverage | E4: Quality | F4: Growth | G4: Balance | H4: Valuation | I4: Risk | J4: Final Score | K4: Confidence | L4: Band | M4: Reason
A5: =IF(Screen_Input!H5="","",Screen_Input!A5) | B5: =IF(Screen_Input!H5="","",Screen_Input!B5) | C5: =IF(Screen_Input!H5="","",IF(OR(Screen_Input!S5<>"verified",Screen_Input!H5=""),"INCOMPLETE","ELIGIBLE")) | D5: =IF($A5="","",COUNT(Screen_Input!I5:Q5)/9) | E5: =IF($A5="","",IF(Screen_Input!K5="","",MIN(100,MAX(0,Screen_Input!K5*100)))) | F5: =IF($A5="","",IF(Screen_Input!O5="","",MIN(100,MAX(0,Screen_Input!O5*100)))) | G5: =IF($A5="","",IF(Screen_Input!N5="","",MIN(100,MAX(0,100-Screen_Input!N5*20)))) | H5: =IF($A5="","",IF(Screen_Input!P5="","",MIN(100,MAX(0,100-Screen_Input!P5*3)))) | I5: =IF($A5="","",IF(Screen_Input!S5<>"verified","",50)) | J5: =IF(OR($A5="",$D5<0.6,$C5<>"ELIGIBLE"),"",ROUND(($E5*0.25+$F5*0.15+$G5*0.10+$H5*0.20+$I5*0.10+50*0.20),1)) | K5: =IF($J5="","",ROUND($D5*100,0)) | L5: =IF($J5="","",IF($J5>=85,"STRONG",IF($J5>=70,"POSITIVE",IF($J5>=55,"WATCH",IF($J5>=40,"WEAK","REJECT"))))) | M5: =IF($A5="","",IF($C5<>"ELIGIBLE","Needs verified source / data coverage",IF($D5<0.8,"Provisional coverage","Screened")))
A6: =IF(Screen_Input!H6="","",Screen_Input!A6) | B6: =IF(Screen_Input!H6="","",Screen_Input!B6) | C6: =IF(Screen_Input!H6="","",IF(OR(Screen_Input!S6<>"verified",Screen_Input!H6=""),"INCOMPLETE","ELIGIBLE")) | D6: =IF($A6="","",COUNT(Screen_Input!I6:Q6)/9) | E6: =IF($A6="","",IF(Screen_Input!K6="","",MIN(100,MAX(0,Screen_Input!K6*100)))) | F6: =IF($A6="","",IF(Screen_Input!O6="","",MIN(100,MAX(0,Screen_Input!O6*100)))) | G6: =IF($A6="","",IF(Screen_Input!N6="","",MIN(100,MAX(0,100-Screen_Input!N6*20)))) | H6: =IF($A6="","",IF(Screen_Input!P6="","",MIN(100,MAX(0,100-Screen_Input!P6*3)))) | I6: =IF($A6="","",IF(Screen_Input!S6<>"verified","",50)) | J6: =IF(OR($A6="",$D6<0.6,$C6<>"ELIGIBLE"),"",ROUND(($E6*0.25+$F6*0.15+$G6*0.10+$H6*0.20+$I6*0.10+50*0.20),1)) | K6: =IF($J6="","",ROUND($D6*100,0)) | L6: =IF($J6="","",IF($J6>=85,"STRONG",IF($J6>=70,"POSITIVE",IF($J6>=55,"WATCH",IF($J6>=40,"WEAK","REJECT"))))) | M6: =IF($A6="","",IF($C6<>"ELIGIBLE","Needs verified source / data coverage",IF($D6<0.8,"Provisional coverage","Screened")))
A7: =IF(Screen_Input!H7="","",Screen_Input!A7) | B7: =IF(Screen_Input!H7="","",Screen_Input!B7) | C7: =IF(Screen_Input!H7="","",IF(OR(Screen_Input!S7<>"verified",Screen_Input!H7=""),"INCOMPLETE","ELIGIBLE")) | D7: =IF($A7="","",COUNT(Screen_Input!I7:Q7)/9) | E7: =IF($A7="","",IF(Screen_Input!K7="","",MIN(100,MAX(0,Screen_Input!K7*100)))) | F7: =IF($A7="","",IF(Screen_Input!O7="","",MIN(100,MAX(0,Screen_Input!O7*100)))) | G7: =IF($A7="","",IF(Screen_Input!N7="","",MIN(100,MAX(0,100-Screen_Input!N7*20)))) | H7: =IF($A7="","",IF(Screen_Input!P7="","",MIN(100,MAX(0,100-Screen_Input!P7*3)))) | I7: =IF($A7="","",IF(Screen_Input!S7<>"verified","",50)) | J7: =IF(OR($A7="",$D7<0.6,$C7<>"ELIGIBLE"),"",ROUND(($E7*0.25+$F7*0.15+$G7*0.10+$H7*0.20+$I7*0.10+50*0.20),1)) | K7: =IF($J7="","",ROUND($D7*100,0)) | L7: =IF($J7="","",IF($J7>=85,"STRONG",IF($J7>=70,"POSITIVE",IF($J7>=55,"WATCH",IF($J7>=40,"WEAK","REJECT"))))) | M7: =IF($A7="","",IF($C7<>"ELIGIBLE","Needs verified source / data coverage",IF($D7<0.8,"Provisional coverage","Screened")))
A8: =IF(Screen_Input!H8="","",Screen_Input!A8) | B8: =IF(Screen_Input!H8="","",Screen_Input!B8) | C8: =IF(Screen_Input!H8="","",IF(OR(Screen_Input!S8<>"verified",Screen_Input!H8=""),"INCOMPLETE","ELIGIBLE")) | D8: =IF($A8="","",COUNT(Screen_Input!I8:Q8)/9) | E8: =IF($A8="","",IF(Screen_Input!K8="","",MIN(100,MAX(0,Screen_Input!K8*100)))) | F8: =IF($A8="","",IF(Screen_Input!O8="","",MIN(100,MAX(0,Screen_Input!O8*100)))) | G8: =IF($A8="","",IF(Screen_Input!N8="","",MIN(100,MAX(0,100-Screen_Input!N8*20)))) | H8: =IF($A8="","",IF(Screen_Input!P8="","",MIN(100,MAX(0,100-Screen_Input!P8*3)))) | I8: =IF($A8="","",IF(Screen_Input!S8<>"verified","",50)) | J8: =IF(OR($A8="",$D8<0.6,$C8<>"ELIGIBLE"),"",ROUND(($E8*0.25+$F8*0.15+$G8*0.10+$H8*0.20+$I8*0.10+50*0.20),1)) | K8: =IF($J8="","",ROUND($D8*100,0)) | L8: =IF($J8="","",IF($J8>=85,"STRONG",IF($J8>=70,"POSITIVE",IF($J8>=55,"WATCH",IF($J8>=40,"WEAK","REJECT"))))) | M8: =IF($A8="","",IF($C8<>"ELIGIBLE","Needs verified source / data coverage",IF($D8<0.8,"Provisional coverage","Screened")))
A9: =IF(Screen_Input!H9="","",Screen_Input!A9) | B9: =IF(Screen_Input!H9="","",Screen_Input!B9) | C9: =IF(Screen_Input!H9="","",IF(OR(Screen_Input!S9<>"verified",Screen_Input!H9=""),"INCOMPLETE","ELIGIBLE")) | D9: =IF($A9="","",COUNT(Screen_Input!I9:Q9)/9) | E9: =IF($A9="","",IF(Screen_Input!K9="","",MIN(100,MAX(0,Screen_Input!K9*100)))) | F9: =IF($A9="","",IF(Screen_Input!O9="","",MIN(100,MAX(0,Screen_Input!O9*100)))) | G9: =IF($A9="","",IF(Screen_Input!N9="","",MIN(100,MAX(0,100-Screen_Input!N9*20)))) | H9: =IF($A9="","",IF(Screen_Input!P9="","",MIN(100,MAX(0,100-Screen_Input!P9*3)))) | I9: =IF($A9="","",IF(Screen_Input!S9<>"verified","",50)) | J9: =IF(OR($A9="",$D9<0.6,$C9<>"ELIGIBLE"),"",ROUND(($E9*0.25+$F9*0.15+$G9*0.10+$H9*0.20+$I9*0.10+50*0.20),1)) | K9: =IF($J9="","",ROUND($D9*100,0)) | L9: =IF($J9="","",IF($J9>=85,"STRONG",IF($J9>=70,"POSITIVE",IF($J9>=55,"WATCH",IF($J9>=40,"WEAK","REJECT"))))) | M9: =IF($A9="","",IF($C9<>"ELIGIBLE","Needs verified source / data coverage",IF($D9<0.8,"Provisional coverage","Screened")))
A10: =IF(Screen_Input!H10="","",Screen_Input!A10) | B10: =IF(Screen_Input!H10="","",Screen_Input!B10) | C10: =IF(Screen_Input!H10="","",IF(OR(Screen_Input!S10<>"verified",Screen_Input!H10=""),"INCOMPLETE","ELIGIBLE")) | D10: =IF($A10="","",COUNT(Screen_Input!I10:Q10)/9) | E10: =IF($A10="","",IF(Screen_Input!K10="","",MIN(100,MAX(0,Screen_Input!K10*100)))) | F10: =IF($A10="","",IF(Screen_Input!O10="","",MIN(100,MAX(0,Screen_Input!O10*100)))) | G10: =IF($A10="","",IF(Screen_Input!N10="","",MIN(100,MAX(0,100-Screen_Input!N10*20)))) | H10: =IF($A10="","",IF(Screen_Input!P10="","",MIN(100,MAX(0,100-Screen_Input!P10*3)))) | I10: =IF($A10="","",IF(Screen_Input!S10<>"verified","",50)) | J10: =IF(OR($A10="",$D10<0.6,$C10<>"ELIGIBLE"),"",ROUND(($E10*0.25+$F10*0.15+$G10*0.10+$H10*0.20+$I10*0.10+50*0.20),1)) | K10: =IF($J10="","",ROUND($D10*100,0)) | L10: =IF($J10="","",IF($J10>=85,"STRONG",IF($J10>=70,"POSITIVE",IF($J10>=55,"WATCH",IF($J10>=40,"WEAK","REJECT"))))) | M10: =IF($A10="","",IF($C10<>"ELIGIBLE","Needs verified source / data coverage",IF($D10<0.8,"Provisional coverage","Screened")))
A11: =IF(Screen_Input!H11="","",Screen_Input!A11) | B11: =IF(Screen_Input!H11="","",Screen_Input!B11) | C11: =IF(Screen_Input!H11="","",IF(OR(Screen_Input!S11<>"verified",Screen_Input!H11=""),"INCOMPLETE","ELIGIBLE")) | D11: =IF($A11="","",COUNT(Screen_Input!I11:Q11)/9) | E11: =IF($A11="","",IF(Screen_Input!K11="","",MIN(100,MAX(0,Screen_Input!K11*100)))) | F11: =IF($A11="","",IF(Screen_Input!O11="","",MIN(100,MAX(0,Screen_Input!O11*100)))) | G11: =IF($A11="","",IF(Screen_Input!N11="","",MIN(100,MAX(0,100-Screen_Input!N11*20)))) | H11: =IF($A11="","",IF(Screen_Input!P11="","",MIN(100,MAX(0,100-Screen_Input!P11*3)))) | I11: =IF($A11="","",IF(Screen_Input!S11<>"verified","",50)) | J11: =IF(OR($A11="",$D11<0.6,$C11<>"ELIGIBLE"),"",ROUND(($E11*0.25+$F11*0.15+$G11*0.10+$H11*0.20+$I11*0.10+50*0.20),1)) | K11: =IF($J11="","",ROUND($D11*100,0)) | L11: =IF($J11="","",IF($J11>=85,"STRONG",IF($J11>=70,"POSITIVE",IF($J11>=55,"WATCH",IF($J11>=40,"WEAK","REJECT"))))) | M11: =IF($A11="","",IF($C11<>"ELIGIBLE","Needs verified source / data coverage",IF($D11<0.8,"Provisional coverage","Screened")))
A12: =IF(Screen_Input!H12="","",Screen_Input!A12) | B12: =IF(Screen_Input!H12="","",Screen_Input!B12) | C12: =IF(Screen_Input!H12="","",IF(OR(Screen_Input!S12<>"verified",Screen_Input!H12=""),"INCOMPLETE","ELIGIBLE")) | D12: =IF($A12="","",COUNT(Screen_Input!I12:Q12)/9) | E12: =IF($A12="","",IF(Screen_Input!K12="","",MIN(100,MAX(0,Screen_Input!K12*100)))) | F12: =IF($A12="","",IF(Screen_Input!O12="","",MIN(100,MAX(0,Screen_Input!O12*100)))) | G12: =IF($A12="","",IF(Screen_Input!N12="","",MIN(100,MAX(0,100-Screen_Input!N12*20)))) | H12: =IF($A12="","",IF(Screen_Input!P12="","",MIN(100,MAX(0,100-Screen_Input!P12*3)))) | I12: =IF($A12="","",IF(Screen_Input!S12<>"verified","",50)) | J12: =IF(OR($A12="",$D12<0.6,$C12<>"ELIGIBLE"),"",ROUND(($E12*0.25+$F12*0.15+$G12*0.10+$H12*0.20+$I12*0.10+50*0.20),1)) | K12: =IF($J12="","",ROUND($D12*100,0)) | L12: =IF($J12="","",IF($J12>=85,"STRONG",IF($J12>=70,"POSITIVE",IF($J12>=55,"WATCH",IF($J12>=40,"WEAK","REJECT"))))) | M12: =IF($A12="","",IF($C12<>"ELIGIBLE","Needs verified source / data coverage",IF($D12<0.8,"Provisional coverage","Screened")))
A13: =IF(Screen_Input!H13="","",Screen_Input!A13) | B13: =IF(Screen_Input!H13="","",Screen_Input!B13) | C13: =IF(Screen_Input!H13="","",IF(OR(Screen_Input!S13<>"verified",Screen_Input!H13=""),"INCOMPLETE","ELIGIBLE")) | D13: =IF($A13="","",COUNT(Screen_Input!I13:Q13)/9) | E13: =IF($A13="","",IF(Screen_Input!K13="","",MIN(100,MAX(0,Screen_Input!K13*100)))) | F13: =IF($A13="","",IF(Screen_Input!O13="","",MIN(100,MAX(0,Screen_Input!O13*100)))) | G13: =IF($A13="","",IF(Screen_Input!N13="","",MIN(100,MAX(0,100-Screen_Input!N13*20)))) | H13: =IF($A13="","",IF(Screen_Input!P13="","",MIN(100,MAX(0,100-Screen_Input!P13*3)))) | I13: =IF($A13="","",IF(Screen_Input!S13<>"verified","",50)) | J13: =IF(OR($A13="",$D13<0.6,$C13<>"ELIGIBLE"),"",ROUND(($E13*0.25+$F13*0.15+$G13*0.10+$H13*0.20+$I13*0.10+50*0.20),1)) | K13: =IF($J13="","",ROUND($D13*100,0)) | L13: =IF($J13="","",IF($J13>=85,"STRONG",IF($J13>=70,"POSITIVE",IF($J13>=55,"WATCH",IF($J13>=40,"WEAK","REJECT"))))) | M13: =IF($A13="","",IF($C13<>"ELIGIBLE","Needs verified source / data coverage",IF($D13<0.8,"Provisional coverage","Screened")))
A14: =IF(Screen_Input!H14="","",Screen_Input!A14) | B14: =IF(Screen_Input!H14="","",Screen_Input!B14) | C14: =IF(Screen_Input!H14="","",IF(OR(Screen_Input!S14<>"verified",Screen_Input!H14=""),"INCOMPLETE","ELIGIBLE")) | D14: =IF($A14="","",COUNT(Screen_Input!I14:Q14)/9) | E14: =IF($A14="","",IF(Screen_Input!K14="","",MIN(100,MAX(0,Screen_Input!K14*100)))) | F14: =IF($A14="","",IF(Screen_Input!O14="","",MIN(100,MAX(0,Screen_Input!O14*100)))) | G14: =IF($A14="","",IF(Screen_Input!N14="","",MIN(100,MAX(0,100-Screen_Input!N14*20)))) | H14: =IF($A14="","",IF(Screen_Input!P14="","",MIN(100,MAX(0,100-Screen_Input!P14*3)))) | I14: =IF($A14="","",IF(Screen_Input!S14<>"verified","",50)) | J14: =IF(OR($A14="",$D14<0.6,$C14<>"ELIGIBLE"),"",ROUND(($E14*0.25+$F14*0.15+$G14*0.10+$H14*0.20+$I14*0.10+50*0.20),1)) | K14: =IF($J14="","",ROUND($D14*100,0)) | L14: =IF($J14="","",IF($J14>=85,"STRONG",IF($J14>=70,"POSITIVE",IF($J14>=55,"WATCH",IF($J14>=40,"WEAK","REJECT"))))) | M14: =IF($A14="","",IF($C14<>"ELIGIBLE","Needs verified source / data coverage",IF($D14<0.8,"Provisional coverage","Screened")))
A15: =IF(Screen_Input!H15="","",Screen_Input!A15) | B15: =IF(Screen_Input!H15="","",Screen_Input!B15) | C15: =IF(Screen_Input!H15="","",IF(OR(Screen_Input!S15<>"verified",Screen_Input!H15=""),"INCOMPLETE","ELIGIBLE")) | D15: =IF($A15="","",COUNT(Screen_Input!I15:Q15)/9) | E15: =IF($A15="","",IF(Screen_Input!K15="","",MIN(100,MAX(0,Screen_Input!K15*100)))) | F15: =IF($A15="","",IF(Screen_Input!O15="","",MIN(100,MAX(0,Screen_Input!O15*100)))) | G15: =IF($A15="","",IF(Screen_Input!N15="","",MIN(100,MAX(0,100-Screen_Input!N15*20)))) | H15: =IF($A15="","",IF(Screen_Input!P15="","",MIN(100,MAX(0,100-Screen_Input!P15*3)))) | I15: =IF($A15="","",IF(Screen_Input!S15<>"verified","",50)) | J15: =IF(OR($A15="",$D15<0.6,$C15<>"ELIGIBLE"),"",ROUND(($E15*0.25+$F15*0.15+$G15*0.10+$H15*0.20+$I15*0.10+50*0.20),1)) | K15: =IF($J15="","",ROUND($D15*100,0)) | L15: =IF($J15="","",IF($J15>=85,"STRONG",IF($J15>=70,"POSITIVE",IF($J15>=55,"WATCH",IF($J15>=40,"WEAK","REJECT"))))) | M15: =IF($A15="","",IF($C15<>"ELIGIBLE","Needs verified source / data coverage",IF($D15<0.8,"Provisional coverage","Screened")))
A16: =IF(Screen_Input!H16="","",Screen_Input!A16) | B16: =IF(Screen_Input!H16="","",Screen_Input!B16) | C16: =IF(Screen_Input!H16="","",IF(OR(Screen_Input!S16<>"verified",Screen_Input!H16=""),"INCOMPLETE","ELIGIBLE")) | D16: =IF($A16="","",COUNT(Screen_Input!I16:Q16)/9) | E16: =IF($A16="","",IF(Screen_Input!K16="","",MIN(100,MAX(0,Screen_Input!K16*100)))) | F16: =IF($A16="","",IF(Screen_Input!O16="","",MIN(100,MAX(0,Screen_Input!O16*100)))) | G16: =IF($A16="","",IF(Screen_Input!N16="","",MIN(100,MAX(0,100-Screen_Input!N16*20)))) | H16: =IF($A16="","",IF(Screen_Input!P16="","",MIN(100,MAX(0,100-Screen_Input!P16*3)))) | I16: =IF($A16="","",IF(Screen_Input!S16<>"verified","",50)) | J16: =IF(OR($A16="",$D16<0.6,$C16<>"ELIGIBLE"),"",ROUND(($E16*0.25+$F16*0.15+$G16*0.10+$H16*0.20+$I16*0.10+50*0.20),1)) | K16: =IF($J16="","",ROUND($D16*100,0)) | L16: =IF($J16="","",IF($J16>=85,"STRONG",IF($J16>=70,"POSITIVE",IF($J16>=55,"WATCH",IF($J16>=40,"WEAK","REJECT"))))) | M16: =IF($A16="","",IF($C16<>"ELIGIBLE","Needs verified source / data coverage",IF($D16<0.8,"Provisional coverage","Screened")))
... A104: =IF(Screen_Input!H104="","",Screen_Input!A104) | B104: =IF(Screen_Input!H104="","",Screen_Input!B104) | C104: =IF(Screen_Input!H104="","",IF(OR(Screen_Input!S104<>"verified",Screen_Input!H104=""),"INCOMPLETE","ELIGIBLE")) | D104: =IF($A104="","",COUNT(Screen_Input!I104:Q104)/9) | E104: =IF($A104="","",IF(Screen_Input!K104="","",MIN(100,MAX(0,Screen_Input!K104*100)))) | F104: =IF($A104="","",IF(Screen_Input!O104="","",MIN(100,MAX(0,Screen_Input!O104*100)))) | G104: =IF($A104="","",IF(Screen_Input!N104="","",MIN(100,MAX(0,100-Screen_Input!N104*20)))) | H104: =IF($A104="","",IF(Screen_Input!P104="","",MIN(100,MAX(0,100-Screen_Input!P104*3)))) | I104: =IF($A104="","",IF(Screen_Input!S104<>"verified","",50)) | J104: =IF(OR($A104="",$D104<0.6,$C104<>"ELIGIBLE"),"",ROUND(($E104*0.25+$F104*0.15+$G104*0.10+$H104*0.20+$I104*0.10+50*0.20),1)) | K104: =IF($J104="","",ROUND($D104*100,0)) | L104: =IF($J104="","",IF($J104>=85,"STRONG",IF($J104>=70,"POSITIVE",IF($J104>=55,"WATCH",IF($J104>=40,"WEAK","REJECT"))))) | M104: =IF($A104="","",IF($C104<>"ELIGIBLE","Needs verified source / data coverage",IF($D104<0.8,"Provisional coverage","Screened")))

Sheet Research_Card
A1: RESEARCH / CARD
A2: Deep-dive structure for one issuer; duplicate the sheet per company
A4: Entity Card | B4: Legal issuer / ticker / exchange / country / currency / fiscal year-end
A5: Research Question | B5: What must this analysis determine?
A6: Thesis | B6: One paragraph supported by source refs
A7: Refuting Evidence | B7: Evidence against the thesis
A8: Business & Moat | B8: Segments, customers, competition, pricing power, durability
A9: Financial Quality | B9: Growth, margins, ROIC, cash conversion, cyclicality
A10: Balance Sheet | B10: Net debt, maturities, liquidity, covenants, off-balance-sheet risks
A11: Valuation | B11: Base / bull / bear assumptions, methods, sensitivity and source refs
A12: Catalysts | B12: Observable events and expected timing
A13: Risks | B13: Risk, severity, likelihood, mitigation
A14: Monitoring | B14: Metrics and thresholds to monitor
A15: Invalidation | B15: Observable evidence that would invalidate the thesis
A16: Conclusion | B16: Research label, confidence, coverage and unresolved data gaps

Sheet Source_Manifest
A1: SOURCE / MANIFEST
A2: Every material value must map to a source reference
A4: Source Ref | B4: Publisher | C4: Title | D4: URL or File | E4: Retrieved At | F4: Data As Of | G4: Publication Date | H4: Period | I4: Currency | J4: Unit | K4: Source Tier | L4: Original / Derived | M4: Claim Coverage | N4: Status | O4: Notes
